{
  "greeting": {
    "title": "이현이의 첫돌",
    "message": "어느덧 1년, 많은 관심과 사랑으로 무럭무럭 자란\n 이현이가 첫 번째 생일을 맞이했습니다.\n소중한 자리에 소중한 분들을 모시고자 합니다.\n바쁘시더라도 귀한 걸음 하시어 \n 이현이의 생일을 축하해 주시면 감사하겠습니다. \n\n정해원 ♥ 정예진",
    "host": {
      "parent": {
        "dad": "정해원",
        "mom": "정예진"
      },
      "groom": {
        "name": "정해원",
        "relation": "아빠",
        "parents": [
          {
            "relation": "아버지",
            "name": "장아빠"
          },
          {
            "relation": "어머니",
            "name": "이엄마"
          }
        ]
      },
      "bride": {
        "name": "네모",
        "relation": "딸",
        "parents": [
          {
            "relation": "아버지",
            "name": "황아빠"
          },
          {
            "relation": "어머니",
            "name": "이엄마"
          }
        ]
      }
    },
    "eventDetail": "2024년 10월 12일 토요일 \n오후 5시 30분\n 전주 파티원 (5층, 하버드홀)"
  },
  "hostInfo": [
    {
      "host": "신랑측",
      "accountInfo": [
        {
          "name": "장세모",
          "relation": "신랑",
          "bank": "카카오뱅크",
          "account": "1234-56-789012",
          "kakaopayAccount": "",
          "tossAccount": ""
        },
        {
          "name": "장아빠",
          "relation": "아버지",
          "bank": "농협",
          "account": "123-45-678901"
        },
        {
          "name": "이엄마",
          "relation": "어머니",
          "bank": "농협",
          "account": "123-45-678901"
        }
      ]
    },
    {
      "host": "신부측",
      "accountInfo": [
        {
          "name": "황네모",
          "relation": "신부",
          "bank": "토스뱅크",
          "account": "1234-5678-9012",
          "kakaopayAccount": "",
          "tossAccount": ""
        },
        {
          "name": "황아빠",
          "relation": "아버지",
          "bank": "농협",
          "account": "123-45-678901"
        },
        {
          "name": "이엄마",
          "relation": "어머니",
          "bank": "농협",
          "account": "123-45-678901"
        }
      ]
    }
  ],
  "mapInfo": {
    "address1": "전주 파티원",
    "address2": "전북 전주시 완산구 효자로 161 5층\n063-224-8849",
    "naverMap": "https://naver.me/GkR0Q0Nr",
    "kakaoMap": "https://kko.to/fEaWr2eNog",
    "lat": 35.819445,
    "lon": 127.1025861
  },
  "locationInfo": [
    {
      "title": "\uD83D\uDCCD 자가용",
      "desc": "\uD83D\uDC49\uD83C\uDFFB 네비게이션에 '전주 파티원'을 검색해주세요"
    },
    {
      "title": "\uD83D\uDCCD 버스",
      "desc": "\uD83D\uDC49\uD83C\uDFFB 전주고속버스터미널에서 차로 약 15분 소요"
    },
    {
      "title": "\uD83D\uDCCD 주차안내",
      "desc": "\uD83D\uDC49\uD83C\uDFFB 주차가능"
    }
  ],
  "emojis": [
    "❤️",
    "💛",
    "💌",
    "🥹",
    "🥳",
    "👰🏻‍",
    "🤵🏻‍️",
    "🤍",
    "✨",
    "💍",
    "💒",
    "💕",
    "😍",
    "🔔",
    "💘"
  ]
}
